todoist_scheduler/__init__.py
todoist_scheduler/archive.py
todoist_scheduler/cli.py
todoist_scheduler/internet.py
todoist_scheduler/main.py
todoist_scheduler/patch.py
todoist_scheduler/utils.py
todoist_scheduler-0.6.0.dist-info/LICENSE
todoist_scheduler-0.6.0.dist-info/METADATA
todoist_scheduler-0.6.0.dist-info/WHEEL
todoist_scheduler-0.6.0.dist-info/entry_points.txt
todoist_scheduler-0.6.0.dist-info/RECORD
