Metadata-Version: 2.1
Name: todoist-scheduler
Version: 0.6.0
Summary: Automatically reschedule tasks in Todoist to reduce the size of the todo lists you see each day.
Home-page: https://github.com/iloveitaly/todoist-scheduler
License: MIT
Keywords: todoist,scheduler,task,management
Author: Michael Bianco
Author-email: mike@mikebian.co
Requires-Python: >=3.10,<4.0
Classifier: License :: OSI Approved :: MIT License
Classifier: Programming Language :: Python :: 3
Classifier: Programming Language :: Python :: 3.10
Classifier: Programming Language :: Python :: 3.11
Classifier: Programming Language :: Python :: 3.12
Requires-Dist: apscheduler (>=3.10.4,<4.0.0)
Requires-Dist: backoff (>=2.2.1,<3.0.0)
Requires-Dist: click (>=8.1.7,<9.0.0)
Requires-Dist: pyjson5 (>=1.6.6,<2.0.0)
Requires-Dist: python-decouple-typed (>=3.11.0,<4.0.0)
Requires-Dist: regex (>=2024.7.24,<2025.0.0)
Requires-Dist: structlog (>=24.4.0,<25.0.0)
Requires-Dist: todoist-api-python (>=2.1.7,<3.0.0)
